{
  "src/routes/+layout.css": {
    "file": "_app/immutable/assets/_layout-45228f0f.css",
    "src": "src/routes/+layout.css"
  },
  "store.css": {
    "file": "_app/immutable/assets/store-fc0256b7.css",
    "src": "store.css"
  },
  "node_modules/@sveltejs/kit/src/runtime/components/error.svelte": {
    "file": "_app/immutable/components/error.svelte-b4e9d7d5.js",
    "src": "node_modules/@sveltejs/kit/src/runtime/components/error.svelte",
    "isEntry": true,
    "imports": [
      "_index-d08134e9.js",
      "_stores-14d407f8.js"
    ]
  },
  "_stores-14d407f8.js": {
    "file": "_app/immutable/chunks/stores-14d407f8.js",
    "imports": [
      "_index-d08134e9.js",
      "_singletons-c484fa62.js"
    ]
  },
  "_Link-bae7be88.js": {
    "file": "_app/immutable/chunks/Link-bae7be88.js",
    "imports": [
      "_index-d08134e9.js"
    ]
  },
  ".svelte-kit/generated/nodes/2.js": {
    "file": "_app/immutable/chunks/2-9c274c93.js",
    "src": ".svelte-kit/generated/nodes/2.js",
    "isDynamicEntry": true,
    "imports": [
      "src/routes/+page.svelte"
    ]
  },
  ".svelte-kit/generated/nodes/3.js": {
    "file": "_app/immutable/chunks/3-7e38123a.js",
    "src": ".svelte-kit/generated/nodes/3.js",
    "isDynamicEntry": true,
    "imports": [
      "src/routes/about/+page.svelte"
    ]
  },
  ".svelte-kit/generated/nodes/4.js": {
    "file": "_app/immutable/chunks/4-160be6d7.js",
    "src": ".svelte-kit/generated/nodes/4.js",
    "isDynamicEntry": true,
    "imports": [
      "src/routes/config/+page.svelte"
    ]
  },
  "src/routes/+layout.ts": {
    "file": "_app/immutable/modules/pages/_layout.ts-55770e65.js",
    "src": "src/routes/+layout.ts",
    "isEntry": true,
    "imports": [
      "__layout-025914ab.js"
    ]
  },
  "src/routes/+layout.svelte": {
    "file": "_app/immutable/components/pages/_layout.svelte-8e9188a9.js",
    "src": "src/routes/+layout.svelte",
    "isEntry": true,
    "imports": [
      "_index-d08134e9.js",
      "_singletons-c484fa62.js",
      "_Link-bae7be88.js",
      "_store-04a82af0.js",
      "_stores-14d407f8.js"
    ],
    "css": [
      "_app/immutable/assets/_layout-45228f0f.css"
    ]
  },
  "_index-d08134e9.js": {
    "file": "_app/immutable/chunks/index-d08134e9.js"
  },
  "_singletons-c484fa62.js": {
    "file": "_app/immutable/chunks/singletons-c484fa62.js",
    "imports": [
      "_index-d08134e9.js"
    ]
  },
  "src/routes/config/+page.svelte": {
    "file": "_app/immutable/components/pages/config/_page.svelte-4f4383c5.js",
    "src": "src/routes/config/+page.svelte",
    "isEntry": true,
    "imports": [
      "_index-d08134e9.js",
      "_store-04a82af0.js"
    ]
  },
  "__layout-025914ab.js": {
    "file": "_app/immutable/chunks/_layout-025914ab.js"
  },
  "src/routes/about/+page.svelte": {
    "file": "_app/immutable/components/pages/about/_page.svelte-a056ce1c.js",
    "src": "src/routes/about/+page.svelte",
    "isEntry": true,
    "imports": [
      "_index-d08134e9.js",
      "_Link-bae7be88.js",
      "_store-04a82af0.js"
    ]
  },
  ".svelte-kit/generated/nodes/1.js": {
    "file": "_app/immutable/chunks/1-c451492c.js",
    "src": ".svelte-kit/generated/nodes/1.js",
    "isDynamicEntry": true,
    "imports": [
      "node_modules/@sveltejs/kit/src/runtime/components/error.svelte"
    ]
  },
  "node_modules/@sveltejs/kit/src/runtime/client/start.js": {
    "file": "_app/immutable/start-c241016e.js",
    "src": "node_modules/@sveltejs/kit/src/runtime/client/start.js",
    "isEntry": true,
    "imports": [
      "_index-d08134e9.js",
      "_singletons-c484fa62.js"
    ],
    "dynamicImports": [
      ".svelte-kit/generated/nodes/0.js",
      ".svelte-kit/generated/nodes/1.js",
      ".svelte-kit/generated/nodes/2.js",
      ".svelte-kit/generated/nodes/3.js",
      ".svelte-kit/generated/nodes/4.js"
    ]
  },
  ".svelte-kit/generated/nodes/0.js": {
    "file": "_app/immutable/chunks/0-1e5a98f2.js",
    "src": ".svelte-kit/generated/nodes/0.js",
    "isDynamicEntry": true,
    "imports": [
      "__layout-025914ab.js",
      "src/routes/+layout.svelte"
    ]
  },
  "_store-04a82af0.js": {
    "file": "_app/immutable/chunks/store-04a82af0.js",
    "imports": [
      "_index-d08134e9.js"
    ],
    "css": [
      "_app/immutable/assets/store-fc0256b7.css"
    ]
  },
  "src/routes/+page.svelte": {
    "file": "_app/immutable/components/pages/_page.svelte-9ff2c3c4.js",
    "src": "src/routes/+page.svelte",
    "isEntry": true,
    "imports": [
      "_index-d08134e9.js",
      "_store-04a82af0.js"
    ]
  }
}